Metadata-Version: 1.0
Name: flask-wx
Version: 0.0.1
Summary: A simple and brief utility tools framework
Home-page: https://github.com/by46/flask_wx
Author: Benjamin Yan
Author-email: ycs_ctbu_2010@126.com
License: The MIT License
Platform: UNKNOWN
